adaptivenms/__init__.py
adaptivenms/square_covering_adaptive_nms.cpython-311-aarch64-linux-gnu.so
adaptivenms/square_covering_adaptive_nms.pyi
adaptivenms/square_covering_adaptive_nms.pyx
adaptive_nms-1.0.0a2.dist-info/METADATA
adaptive_nms-1.0.0a2.dist-info/WHEEL
adaptive_nms-1.0.0a2.dist-info/top_level.txt
adaptive_nms-1.0.0a2.dist-info/RECORD
adaptive_nms-1.0.0a2.dist-info/licenses/LICENSE
