Metadata-Version: 2.1
Name: adaptive-nms
Version: 1.0.0a2
Summary: Cython implementation of Square Covering approach for Adaptive 2D Keypoints Non-Maximum Suppression 
Author: Tolga Demirdal
License: MIT License
Project-URL: Homepage, https://github.com/shadymeowy/adaptive-nms
Project-URL: Repository, https://github.com/shadymeowy/adaptive-nms
License-File: LICENSE
Requires-Dist: numpy
